[
  {
    "id": "1772303457277-zg6bte",
    "timestamp": "2026-02-28T18:30:57.276Z",
    "totalFiles": 64,
    "totalLines": 9419,
    "commentRatio": 9,
    "totalSize": 398108,
    "techDebtScore": 4331
  },
  {
    "id": "1772303479875-s2d2uh",
    "timestamp": "2026-02-28T18:31:19.874Z",
    "totalFiles": 64,
    "totalLines": 9419,
    "commentRatio": 9,
    "totalSize": 398108,
    "techDebtScore": 4331
  },
  {
    "id": "1772304551651-b5nyz1",
    "timestamp": "2026-02-28T18:49:11.651Z",
    "totalFiles": 64,
    "totalLines": 9425,
    "commentRatio": 9.1,
    "totalSize": 398467,
    "techDebtScore": 4331
  },
  {
    "id": "1772304665514-xoti0t",
    "timestamp": "2026-02-28T18:51:05.514Z",
    "totalFiles": 64,
    "totalLines": 9425,
    "commentRatio": 9.1,
    "totalSize": 398467,
    "techDebtScore": 4331
  },
  {
    "id": "1772304802567-7yrcvy",
    "timestamp": "2026-02-28T18:53:22.566Z",
    "totalFiles": 65,
    "totalLines": 9441,
    "commentRatio": 9,
    "totalSize": 399019,
    "techDebtScore": 4347
  },
  {
    "id": "1772304914676-4i7c3t",
    "timestamp": "2026-02-28T18:55:14.675Z",
    "totalFiles": 65,
    "totalLines": 9441,
    "commentRatio": 9,
    "totalSize": 399019,
    "techDebtScore": 4347
  },
  {
    "id": "1772305111586-a0k2z3",
    "timestamp": "2026-02-28T18:58:31.586Z",
    "totalFiles": 66,
    "totalLines": 10618,
    "commentRatio": 8,
    "totalSize": 424357,
    "techDebtScore": 5520
  },
  {
    "id": "1772308077799-o4092v",
    "timestamp": "2026-02-28T19:47:57.798Z",
    "totalFiles": 66,
    "totalLines": 10630,
    "commentRatio": 8,
    "totalSize": 425835,
    "techDebtScore": 5521
  },
  {
    "id": "1772308876909-j6ooma",
    "timestamp": "2026-02-28T20:01:16.908Z",
    "totalFiles": 66,
    "totalLines": 10639,
    "commentRatio": 8,
    "totalSize": 426197,
    "techDebtScore": 5523
  }
]